ghostfft/__init__.py
ghostfft/component.py
ghostfft/fft.py
ghostfft/fp.py
ghostfft/generators.py
ghostfft/misc.py
ghostfft/pfb.py
ghostfft/serial.py
ghostfft/ufp.py
ghostfft/utils.py
ghostfft-0.3.0.dist-info/LICENSE
ghostfft-0.3.0.dist-info/METADATA
ghostfft-0.3.0.dist-info/WHEEL
ghostfft-0.3.0.dist-info/RECORD
