Metadata-Version: 2.1
Name: ghostfft
Version: 0.3.0
Summary: A tool to simulate behaviour of CASPER Simulink blocks with bit accuracy.
Author: Vadym Bidula
Author-email: vadym.bidula@gmail.com
Requires-Python: >=3.10,<4.0
Classifier: Programming Language :: Python :: 3
Classifier: Programming Language :: Python :: 3.10
Classifier: Programming Language :: Python :: 3.11
Classifier: Programming Language :: Python :: 3.12
Classifier: Programming Language :: Python :: 3.13
Requires-Dist: hdf5storage (>=0.1.19,<0.2.0)
Requires-Dist: numpy (>=2.1.3,<3.0.0)
Requires-Dist: setuptools (>=70.2.0,<71.0.0)
Requires-Dist: tqdm (>=4.66.2,<5.0.0)
